flask_session/__init__.py
flask_session/sessions.py
flask_providers_session-0.4.1.dist-info/LICENSE
flask_providers_session-0.4.1.dist-info/WHEEL
flask_providers_session-0.4.1.dist-info/METADATA
flask_providers_session-0.4.1.dist-info/RECORD
