Metadata-Version: 2.1
Name: flask-providers-session
Version: 0.4.1
Summary: Fork version flask session
Author: benbenbang
Author-email: bn@benbenbang.io
Maintainer: benbenbang
Maintainer-email: bn@benbenbang.io
Requires-Python: >=3.7.2,<4.0.0
Classifier: Programming Language :: Python :: 3
Classifier: Programming Language :: Python :: 3.8
Classifier: Programming Language :: Python :: 3.9
Classifier: Programming Language :: Python :: 3.10
Classifier: Programming Language :: Python :: 3.11
Provides-Extra: all
Provides-Extra: cache
Provides-Extra: mongo
Provides-Extra: redis
Provides-Extra: sqlalechmey
Requires-Dist: cachelib (>=0.9.0); extra == "all" or extra == "cache"
Requires-Dist: flask-sqlalchemy (>=1.0.0); extra == "all" or extra == "sqlalechmey"
Requires-Dist: pylibmc (>=1.6.3,<2.0.0)
Requires-Dist: pymongo (>=4.3.2); extra == "all" or extra == "mongo"
Requires-Dist: redis (>=4.3.4); extra == "all" or extra == "redis"
